mareep/__init__.py
mareep/__main__.py
mareep/app.py
mareep/function.py
mareep/renderer.py
mareep/loaders/__init__.py
mareep/loaders/loader.py
mareep/loaders/json_loader/__init__.py
mareep/loaders/json_loader/loader.py
mareep/loaders/yaml_loader/__init__.py
mareep/loaders/yaml_loader/loader.py
mareep-0.0.6.dist-info/METADATA
mareep-0.0.6.dist-info/WHEEL
mareep-0.0.6.dist-info/entry_points.txt
mareep-0.0.6.dist-info/top_level.txt
mareep-0.0.6.dist-info/RECORD
