Metadata-Version: 2.1
Name: mareep
Version: 0.0.6
Summary: mareep
Home-page: https://github.com/NgHoangDat/mareep.git
Author: nghoangdat
Author-email: 18.hoang.dat.12@gmail.com
License: UNKNOWN
Download-URL: https://github.com/NgHoangDat/mareep/archive/v0.0.6.tar.gz
Platform: UNKNOWN
Classifier: Programming Language :: Python :: 3
Classifier: License :: OSI Approved :: MIT License
Classifier: Operating System :: OS Independent
Requires-Python: >=3.6
Requires-Dist: typer
Requires-Dist: cowsay
Requires-Dist: PyYAML
Requires-Dist: Jinja2
Requires-Dist: mousse
Provides-Extra: dev
Requires-Dist: black ; extra == 'dev'
Provides-Extra: yaml
Requires-Dist: pyyaml ; extra == 'yaml'
